url_checker/__init__.py
url_checker/core.py
robots_checker-1.2.3.dist-info/METADATA
robots_checker-1.2.3.dist-info/WHEEL
robots_checker-1.2.3.dist-info/top_level.txt
robots_checker-1.2.3.dist-info/RECORD
